[
  {
    "id": "src.main",
    "name": "main",
    "stats": {
      "size": 345360,
      "gzipSize": 45190
    }
  },
  {
    "id": "node_modules.main",
    "name": "node_modules [main]",
    "stats": {
      "size": 151275,
      "gzipSize": 45313
    }
  },
  {
    "id": "atlaskit.core.main",
    "name": "main",
    "stats": {
      "size": 108480,
      "gzipSize": 27619
    }
  },
  {
    "id": "combined.main",
    "name": "main",
    "stats": {
      "size": 602269,
      "gzipSize": 116731
    }
  }
]