[
  {
    "id": "src.main",
    "name": "main",
    "stats": {
      "size": 588318,
      "gzipSize": 154237
    }
  },
  {
    "id": "src.async",
    "name": "async",
    "stats": {
      "size": 21739,
      "gzipSize": 5622
    }
  },
  {
    "id": "node_modules.main",
    "name": "node_modules [main]",
    "stats": {
      "size": 698545,
      "gzipSize": 202174
    }
  },
  {
    "id": "node_modules.async",
    "name": "node_modules [async]",
    "stats": {
      "size": 247222,
      "gzipSize": 68875
    }
  },
  {
    "id": "atlaskit.core.main",
    "name": "main",
    "stats": {
      "size": 432656,
      "gzipSize": 93140
    }
  },
  {
    "id": "atlaskit.core.async",
    "name": "async",
    "stats": {
      "size": 193444,
      "gzipSize": 40113
    }
  },
  {
    "id": "atlaskit.editor.main",
    "name": "main",
    "stats": {
      "size": 119797,
      "gzipSize": 29000
    }
  },
  {
    "id": "atlaskit.elements.main",
    "name": "main",
    "stats": {
      "size": 141167,
      "gzipSize": 38202
    }
  },
  {
    "id": "atlaskit.elements.async",
    "name": "async",
    "stats": {
      "size": 36686,
      "gzipSize": 10075
    }
  },
  {
    "id": "atlaskit.media.main",
    "name": "main",
    "stats": {
      "size": 237029,
      "gzipSize": 54277
    }
  },
  {
    "id": "atlaskit.media.async",
    "name": "async",
    "stats": {
      "size": 766688,
      "gzipSize": 190991
    }
  },
  {
    "id": "atlaskit.teamwork-ecosystem.main",
    "name": "main",
    "stats": {
      "size": 624,
      "gzipSize": 367
    }
  },
  {
    "id": "combined.main",
    "name": "main",
    "stats": {
      "size": 2210504,
      "gzipSize": 585978
    }
  },
  {
    "id": "combined.async",
    "name": "async",
    "stats": {
      "size": 1264057,
      "gzipSize": 317563
    }
  }
]
