[
  {
    "id": "src.main",
    "name": "main",
    "stats": {
      "size": 666458,
      "gzipSize": 176064
    }
  },
  {
    "id": "src.async",
    "name": "async",
    "stats": {
      "size": 38850,
      "gzipSize": 9270
    }
  },
  {
    "id": "node_modules.main",
    "name": "node_modules [main]",
    "stats": {
      "size": 710588,
      "gzipSize": 207449
    }
  },
  {
    "id": "node_modules.async",
    "name": "node_modules [async]",
    "stats": {
      "size": 1429136,
      "gzipSize": 407616
    }
  },
  {
    "id": "atlaskit.core.main",
    "name": "main",
    "stats": {
      "size": 223876,
      "gzipSize": 49272
    }
  },
  {
    "id": "atlaskit.core.async",
    "name": "async",
    "stats": {
      "size": 165497,
      "gzipSize": 31309
    }
  },
  {
    "id": "atlaskit.editor.main",
    "name": "main",
    "stats": {
      "size": 131626,
      "gzipSize": 30946
    }
  },
  {
    "id": "atlaskit.elements.main",
    "name": "main",
    "stats": {
      "size": 146010,
      "gzipSize": 39785
    }
  },
  {
    "id": "atlaskit.elements.async",
    "name": "async",
    "stats": {
      "size": 39972,
      "gzipSize": 10865
    }
  },
  {
    "id": "atlaskit.media.main",
    "name": "main",
    "stats": {
      "size": 67551,
      "gzipSize": 15892
    }
  },
  {
    "id": "atlaskit.media.async",
    "name": "async",
    "stats": {
      "size": 1022652,
      "gzipSize": 250530
    }
  },
  {
    "id": "atlaskit.teamwork-ecosystem.main",
    "name": "main",
    "stats": {
      "size": 624,
      "gzipSize": 367
    }
  },
  {
    "id": "combined.main",
    "name": "main",
    "stats": {
      "size": 1938117,
      "gzipSize": 530824
    }
  },
  {
    "id": "combined.async",
    "name": "async",
    "stats": {
      "size": 2694492,
      "gzipSize": 712755
    }
  }
]